metaformer_gpt/__init__.py
metaformer_gpt/autoregressive_wrapper.py
metaformer_gpt/metaformer_gpt.py
metaformer_gpt-0.0.5.dist-info/LICENSE
metaformer_gpt-0.0.5.dist-info/METADATA
metaformer_gpt-0.0.5.dist-info/WHEEL
metaformer_gpt-0.0.5.dist-info/top_level.txt
metaformer_gpt-0.0.5.dist-info/RECORD
