Metadata-Version: 2.1
Name: metaformer-gpt
Version: 0.0.5
Summary: Metaformer - GPT
Home-page: https://github.com/lucidrains/metaformer-gpt
Author: Phil Wang
Author-email: lucidrains@gmail.com
License: MIT
Keywords: artificial intelligence,deep learning,transformers,attention-less
Classifier: Development Status :: 4 - Beta
Classifier: Intended Audience :: Developers
Classifier: Topic :: Scientific/Engineering :: Artificial Intelligence
Classifier: License :: OSI Approved :: MIT License
Classifier: Programming Language :: Python :: 3.6
License-File: LICENSE
Requires-Dist: einops (>=0.4)
Requires-Dist: scipy
Requires-Dist: torch (>=1.6)
